CHANGES.txt
MANIFEST.in
README.rst
setup.py
isotoma/__init__.py
isotoma.egglayer.egg-info/PKG-INFO
isotoma.egglayer.egg-info/SOURCES.txt
isotoma.egglayer.egg-info/dependency_links.txt
isotoma.egglayer.egg-info/namespace_packages.txt
isotoma.egglayer.egg-info/not-zip-safe
isotoma.egglayer.egg-info/requires.txt
isotoma.egglayer.egg-info/top_level.txt
isotoma/egglayer/__init__.py
isotoma/egglayer/package.py
isotoma/egglayer/plone.py
isotoma/egglayer/tests.py
isotoma/egglayer/templates/PKG-INFO.j2
isotoma/egglayer/templates/entry_points.txt.j2
isotoma/egglayer/templates/setup.py.j2
isotoma/egglayer/templates/plone/configure.zcml.j2
isotoma/egglayer/templates/plone/metadata.xml.j2
isotoma/egglayer/templates/plone/profiles.zcml.j2
isotoma/egglayer/templates/plone/properties.xml.j2
isotoma/egglayer/templates/plone/propertiestool.xml.j2
isotoma/egglayer/templates/plone/registry.xml.j2