Metadata-Version: 1.0
Name: isotoma.egglayer
Version: 0.0.4
Summary: Utility for packaging things as eggs without setuptools
Home-page: http://pypi.python.org/pypi/isotoma.egglayer
Author: John Carr
Author-email: john.carr@isotoma.com
License: Apache Software License
Keywords: egg builder packaging
Platform: UNKNOWN
Classifier: Development Status :: 4 - Beta
Classifier: Intended Audience :: Developers
Classifier: Operating System :: OS Independent
Classifier: Programming Language :: Python
Classifier: Topic :: Software Development :: Libraries :: Python Modules
Classifier: Topic :: System :: Software Distribution
Classifier: License :: OSI Approved :: Apache Software License
